{
  "title": "FS244 Ottilie Normalcamperin",
  "number": 244,
  "date": "2019-11-28",
  "url": "https://freakshow.fm/fs244-ottilie-normalcamperin",
  "duration": [
    3,
    55,
    0
  ],
  "description": "Camping — Mobilfunktarife — Command Line Tools — Editor Tools — Cybertruck — 10 GBit Ethernet — Apple Pay — German Engineering",
  "speakers": [
    "Tim Pritlove",
    "Letty",
    "hukl",
    "Clemens Schrimpe"
  ],
  "chapters": [
    "Intro",
    "Vorgeplänkel",
    "Begrüßung",
    "Pimp My Caravan",
    "Mobilfunktarife",
    "IP-Erreichbarkeit im Mobilfunknetz",
    "Command Line Tools",
    "VSCode / Language Server Protocol",
    "Cloud-based Apps",
    "Command Line Tips contd.",
    "Command Line Heroes",
    "Shells",
    "DAW und Tools",
    "Applekram",
    "Tesla fahren",
    "Tesla Cybertruck",
    "ScanSnap Home",
    ".org Domains",
    "10 Gbit Ethernet",
    "LED Farbwiedergabewerte",
    "Lichtkunst",
    "Apple Pay und mobiles Bezahlen",
    "Deutsche WLAN",
    "Fair Queueing",
    "Ausklang mit Jacinda Ardern",
    "Bonus Track"
  ]
}