{
  "episodeNumber": 50,
  "title": "MM050 Fail Center",
  "extractedAt": "2025-12-27T09:45:05.762Z",
  "topics": [
    {
      "topic": "Jubiläumsausgabe des Podcasts",
      "keywords": [
        "Jubiläum",
        "50. Episode",
        "Feier"
      ]
    },
    {
      "topic": "Vollbesetzung des Teams",
      "keywords": [
        "Team",
        "Vollbesetzung",
        "Diskussion"
      ]
    },
    {
      "topic": "Alberne und ausgelassene Stimmung",
      "keywords": [
        "Humor",
        "Spaß",
        "Unterhaltung"
      ]
    },
    {
      "topic": "Längere Episode",
      "keywords": [
        "Überlange Episode",
        "Inhalt",
        "Dauer"
      ]
    },
    {
      "topic": "Rückblick auf vergangene Episoden",
      "keywords": [
        "Rückblick",
        "Vergangenheit",
        "Highlights"
      ]
    },
    {
      "topic": "Zukunft des Podcasts",
      "keywords": [
        "Zukunft",
        "Entwicklung",
        "Pläne"
      ]
    },
    {
      "topic": "Interaktion mit der Hörerschaft",
      "keywords": [
        "Hörer",
        "Feedback",
        "Interaktion"
      ]
    },
    {
      "topic": "Technologische Themen",
      "keywords": [
        "Technologie",
        "Gadgets",
        "Innovation"
      ]
    },
    {
      "topic": "Mobile Geräte und Apps",
      "keywords": [
        "Mobile Geräte",
        "Apps",
        "Nutzung"
      ]
    },
    {
      "topic": "Persönliche Anekdoten der Hosts",
      "keywords": [
        "Anekdoten",
        "Persönliches",
        "Erfahrungen"
      ]
    },
    {
      "topic": "Aktuelle Trends in der Tech-Welt",
      "keywords": [
        "Trends",
        "Technologie",
        "Marktentwicklung"
      ]
    },
    {
      "topic": "Kulturelle Einflüsse auf Technologie",
      "keywords": [
        "Kultur",
        "Einflüsse",
        "Technologie"
      ]
    },
    {
      "topic": "Unterhaltung durch technische Missgeschicke",
      "keywords": [
        "Missgeschicke",
        "Unterhaltung",
        "Pannen"
      ]
    },
    {
      "topic": "Erfahrungen mit neuen Produkten",
      "keywords": [
        "Produkte",
        "Erfahrungen",
        "Bewertungen"
      ]
    },
    {
      "topic": "Zuhörerfragen und Antworten",
      "keywords": [
        "Fragen",
        "Antworten",
        "Zuhörer"
      ]
    },
    {
      "topic": "Einblicke in die Podcast-Produktion",
      "keywords": [
        "Produktion",
        "Hinter den Kulissen",
        "Prozess"
      ]
    },
    {
      "topic": "Humorvolle Diskussionen über Technik",
      "keywords": [
        "Diskussion",
        "Humor",
        "Technik"
      ]
    },
    {
      "topic": "Einfluss von Social Media auf Podcasts",
      "keywords": [
        "Social Media",
        "Einfluss",
        "Podcasts"
      ]
    },
    {
      "topic": "Community-Building rund um den Podcast",
      "keywords": [
        "Community",
        "Aufbau",
        "Zuhörerbindung"
      ]
    }
  ]
}