{
  "episodeNumber": 583,
  "title": "WR583 Anonyme Astronomiker",
  "extractedAt": "2026-01-04T19:07:10.776Z",
  "dataSource": "description",
  "topics": [
    {
      "topic": "Zweite Erde",
      "subject": {
        "coarse": "Astronomie",
        "fine": "Exoplaneten"
      },
      "summary": "",
      "summaryMeta": {
        "transcriptFound": false,
        "transcriptFile": "583-ts.json"
      }
    },
    {
      "topic": "Lebensfreundliche Venus",
      "subject": {
        "coarse": "Astronomie",
        "fine": "Planetologie"
      },
      "summary": "",
      "summaryMeta": {
        "transcriptFound": false,
        "transcriptFile": "583-ts.json"
      }
    },
    {
      "topic": "Sternengeschichten",
      "subject": {
        "coarse": "Astronomie",
        "fine": "Mythologie"
      },
      "summary": "",
      "summaryMeta": {
        "transcriptFound": false,
        "transcriptFile": "583-ts.json"
      }
    },
    {
      "topic": "Chemtrails",
      "subject": {
        "coarse": "Umwelt",
        "fine": "Verschwörungstheorien"
      },
      "summary": "",
      "summaryMeta": {
        "transcriptFound": false,
        "transcriptFile": "583-ts.json"
      }
    },
    {
      "topic": "Quantensatellit",
      "subject": {
        "coarse": "Technologie",
        "fine": "Quantenkommunikation"
      },
      "summary": "",
      "summaryMeta": {
        "transcriptFound": false,
        "transcriptFile": "583-ts.json"
      }
    },
    {
      "topic": "Übernutzung der Erde",
      "subject": {
        "coarse": "Umwelt",
        "fine": "Ressourcennutzung"
      },
      "summary": "",
      "summaryMeta": {
        "transcriptFound": false,
        "transcriptFile": "583-ts.json"
      }
    },
    {
      "topic": "Übergewichtige Gehirne",
      "subject": {
        "coarse": "Gesundheit",
        "fine": "Ernährung"
      },
      "summary": "",
      "summaryMeta": {
        "transcriptFound": false,
        "transcriptFile": "583-ts.json"
      }
    },
    {
      "topic": "Reiches Ungeziefer",
      "subject": {
        "coarse": "Biologie",
        "fine": "Ökologie"
      },
      "summary": "",
      "summaryMeta": {
        "transcriptFound": false,
        "transcriptFile": "583-ts.json"
      }
    },
    {
      "topic": "Gut & Böse",
      "subject": {
        "coarse": "Philosophie",
        "fine": "Ethik"
      },
      "summary": "",
      "summaryMeta": {
        "transcriptFound": false,
        "transcriptFile": "583-ts.json"
      }
    },
    {
      "topic": "Hunger und Lernen",
      "subject": {
        "coarse": "Gesellschaft",
        "fine": "Bildung"
      },
      "summary": "",
      "summaryMeta": {
        "transcriptFound": false,
        "transcriptFile": "583-ts.json"
      }
    }
  ],
  "extendedAt": "2026-01-04T19:28:23.961Z",
  "transcriptFound": false,
  "transcriptFile": "583-ts.json"
}
