{
  "episodeNumber": 12,
  "title": "RZ012 Sigmund J채hn",
  "generatedAt": "2026-01-05T15:18:06.275Z",
  "dataSource": "extended-topics",
  "radarChart": {
    "values": {
      "Raumfahrt": 0,
      "Astronomie": 0,
      "Wissenschaft": 0,
      "Technologie": 0,
      "Space": 1,
      "Science": 0,
      "Technology": 0,
      "Physik": 0,
      "Forschung": 0,
      "Biologie": 0,
      "Research": 0,
      "Wirtschaft": 0
    },
    "durations": {
      "Raumfahrt": 0,
      "Astronomie": 0,
      "Wissenschaft": 0,
      "Technologie": 0,
      "Space": 0,
      "Science": 0,
      "Technology": 0,
      "Physik": 0,
      "Forschung": 0,
      "Biologie": 0,
      "Research": 0,
      "Wirtschaft": 0
    },
    "topicCounts": {
      "Raumfahrt": 0,
      "Astronomie": 0,
      "Wissenschaft": 0,
      "Technologie": 0,
      "Space": 5,
      "Science": 0,
      "Technology": 0,
      "Physik": 0,
      "Forschung": 0,
      "Biologie": 0,
      "Research": 0,
      "Wirtschaft": 0
    },
    "totalDurationSec": 0,
    "totalTopics": 5
  },
  "timeline": [
    {
      "subject": "Space",
      "startSec": null,
      "endSec": null,
      "durationSec": null,
      "topic": "R체ckblick auf die bemannte Raumfahrt",
      "fineSubject": "Manned Spaceflight",
      "topicIndex": 0,
      "untimed": true
    },
    {
      "subject": "Space",
      "startSec": null,
      "endSec": null,
      "durationSec": null,
      "topic": "Juri Gagarin und die Wostok 1",
      "fineSubject": "Historical Missions",
      "topicIndex": 1,
      "untimed": true
    },
    {
      "subject": "Space",
      "startSec": null,
      "endSec": null,
      "durationSec": null,
      "topic": "Sigmund J채hn als erster deutscher Raumfahrer",
      "fineSubject": "Astronauts",
      "topicIndex": 2,
      "untimed": true
    },
    {
      "subject": "Space",
      "startSec": null,
      "endSec": null,
      "durationSec": null,
      "topic": "Raumstationen und Langzeitmissionen",
      "fineSubject": "Space Stations",
      "topicIndex": 3,
      "untimed": true
    },
    {
      "subject": "Space",
      "startSec": null,
      "endSec": null,
      "durationSec": null,
      "topic": "Rolle von Sigmund J채hn nach der Wende",
      "fineSubject": "Astronaut Training",
      "topicIndex": 4,
      "untimed": true
    }
  ]
}
